modulemap/__init__.py
modulemap/modulemap.py
modulemap-0.0.2.dist-info/LICENSE
modulemap-0.0.2.dist-info/METADATA
modulemap-0.0.2.dist-info/WHEEL
modulemap-0.0.2.dist-info/top_level.txt
modulemap-0.0.2.dist-info/RECORD
