Metadata-Version: 2.1
Name: modulemap
Version: 0.0.2
Summary: A lightweight option for creating json description files of Python modules
Home-page: https://github.com/singram12/ModuleMap
Author: Sam Ingram
Author-email: sp_ingram12@yahoo.co.uk
License: UNKNOWN
Platform: UNKNOWN
Classifier: Programming Language :: Python :: 3
Classifier: License :: OSI Approved :: MIT License
Classifier: Operating System :: OS Independent
Requires-Python: >=3.5
Requires-Dist: jsondiff (>=1.2.0)
